{"Place of Birth":"Azamgarh (Uttar Pradesh)","Social And Cultural Activities":"Social work","No.of Daughters":"2","Mother's Name":"Smt. Umrai Chauhan","Party Name":"Bahujan Samaj Party(BSP)","Profession":"Agriculturist Political and Social Worker","Favourite Pastime and Recreation":"Reading books on social issues","Constituency":"Ghosi (Uttar Pradesh )","Date of Birth":"25 Jul 1963","Educational Qualifications":"Graduate Educated at D.A.V. Degree College, Azamgarh, Uttar Pradesh","No. of Sons":"2","Other Information":"Member, National Executive Committee, Samajwadi Party","Present Address":"\n30, Canning Lane,\nNew Delhi - 110 001\nTels. 9013180777 (M)\n\n\n\n","Email Address :":"ds.chauhan@sansad.nic.in","Name":"Chauhan,Shri Dara Singh","Marital Status":"Married","Image":"http:\/\/164.100.47.132\/mpimage\/photo\/4304.jpg","Positions Held":"\nNov. 1996\nElected to Rajya Sabha\n\n1998-99\nMember, Committee on Petroleum and Natural Gas\n\n1998-2001\nMember, Consultative Committee, Ministry of Coal\n\nApril 2000\nRe-elected to Rajya Sabha (2nd term)\n\nMay 2000-Feb. 2004\nMember, Committee on Energy\n\nJan. 2002-Feb. 2004\nMember, Consultative Committee, Ministry of Coal and Mines\n\nAug. 2004-April 2005\nMember, Committee on Transport, Tourism and Culture\n\nSept. 2004\nMember, Committee on Members of Parliament Local Area Development Scheme (Rajya Sabha)\n\nOct. 2004\nMember, Consultative Committee, Ministry of Defence\n\nApril 2005\nMember, Committee on Energy\n\n2009\nElected to 15th Lok Sabha\nLeader, Bahujan Samaj Parliamentary Party, Lok Sabha\n\n26 June 2009\nMember, Business Advisory Committee\n\n4 Aug. 2009\nMember, Committee on Installation of Potraits\/Statues of National Leaders and Parliamentarians in Parliament House Complex\n\n31 Aug. 2009\nChairman, Committee on Social Justice and Empowerment\n\n4 Sept. 2009\nMember, Committee on Secruity in Parliament Complex\n\n23 Sept. 2009\nMember, Committee on Government Assurances\n\n19 Oct. 2009\nMember, General Purposes Committee\n\n1 Dec. 2009\nMember, Joint Committee on Office of Profit\n\n3 May 2013\nMemberCommittee on Welfare of Other Backward Classes (OBCs)\n","Permanent Address":"\nVill. Gelwara, P.O. - Jafarpur\nDist. - Azamgarh, Uttar Pradesh\nTels. 9936092622 (M), 9451401094 (M)\n\n\n\n","Father's Name":"Shri Ram Kishun Chauhan","Spouse's Name":"Smt. Disha Chauhan"}