{"Place of Birth":"Shikaripura, Distt. - Shivamogga (Karnataka)","Sports and Clubs":"Shuttle cock-Badminton","Social And Cultural Activities":"Promoter of cultural activities in Shivamogga district; and running a cultural organisation `Sourabha`","Mother's Name":"Smt. Mythri Devi","Party Name":"Bharatiya Janata Party(BJP)","Profession":"Political and Social Worker","Date of Marriage":"12 Feb 1997","Favourite Pastime and Recreation":"Reading novels","Constituency":"Shimoga (Karnataka )","Date of Birth":"16 Aug 1973","Educational Qualifications":"B.B.M. Educated at A.T.N.C.C.,Shivamogga,Karnataka","No. of Sons":"2","Other Information":"Running several educational institutions like Prerana Education of Science and Information Technology (PESIT)and Nursing College,offering B.C.A., B.B.M., B.Ed., D.Ed.","Present Address":"\n70, South Avenue,\nNew Delhi - 110011\nTelefax. (011) 23010424 9013180239, 9449827633 (M)\n\n\n\n","Email Address :":"raghuby@gmail.com","Name":"Yeddyurappa,Shri Raghavendra","Marital Status":"Married","Countries Visited":"Widelty travelled","Image":"http:\/\/164.100.47.132\/mpimage\/photo\/4570.jpg","Positions Held":"\n2009\nElected to 15th Lok Sabha\n\n31 Aug. 2009\nMember, Committee on Industry\n","Permanent Address":"\nMythri Nivasa, Malerakeri,\nShikaripura, Karnataka\nTel. (08187) 222256, (08182) 255427, 9731853100 (M) Fax. (08187) 222935\n\n\n\n","Father's Name":"Shri Bookanakere Yeddyurappa","Spouse's Name":"Smt. R. Tejaswini"}