{"Place of Birth":"Hyderabad (Andhra Pradesh)","Sports and Clubs":"Playing cricket","Mother's Name":"Smt. Yousuf Sultana","Party Name":"Indian National Congress(INC)","Profession":"Sportsperson","Date of Marriage":"14 Nov 1996","Favourite Pastime and Recreation":"Watching different sports on TV","Literary Artistic & Scientific Accomplishments":"Reading books on sports","Constituency":"Moradabad (Uttar Pradesh )","Special Interests":"Wildlife, sports and travelling","Date of Birth":"08 Feb 1963","Educational Qualifications":"B.Com. Educated at Nizam College,Osmania University, Hyderabad, Andhra Pradesh","No. of Sons":"2","Present Address":"\nC-1\/12, Lodhi Garden,\nNew Delhi - 110 003\nTels. (011) 24647790, 9013180193 (M)\n\n\n\n","Name":"Azharuddin,Shri Mohammed","Marital Status":"Married","Countries Visited":"Widely travelled","Image":"http:\/\/164.100.47.132\/mpimage\/photo\/4265.jpg","Positions Held":"\n2009\nElected to 15th Lok Sabha\n\n31 Aug. 2009\nMember, Committee on Energy\n","Permanent Address":"\nHouse No. 6-3-252\/1\/6, Flat No. 501 Nest Apartments, Eram Manzil\nHyderabad - 500 082, Andhra Pradesh\nTels. (040) 23398240\n\n\n\n","Father's Name":"Shri Mohammed Azizuddin","Spouse's Name":"Smt. Sangeeta Azharuddin"}